{"total":4346,"skinList":[{"id":10320,"skinID":"1B8C4652-4B51-72E4-51FB-D387980205E9","isSetSkin":false,"skinSetName":"\u6975\u6A02\u4E4B\u9470","name":"\u6975\u6A02\u4E4B\u9470","name_SC":"\u5929\u5802\u4E4B\u94A5","weaponName":"\u8FD1\u6218","weaponName_SC":"\u8FD1\u6218","picUrl":"https://img1b.gamersky.com/new/recommend/2026/05/06/origin_3845393_2058479.png","sliderImageUrl":"","price":0,"priceInDiscount":0,"discountExpireTime":"1970-01-01T08:00:00","discountStartTime":"1970-01-01T08:00:00","priceInChianMainland":0,"priceInDiscountInChianMainland":0,"discountExpireTimeInChianMainland":"1970-01-01T08:00:00","discountStartTimeInChianMainland":"1970-01-01T08:00:00","weaponType":5,"skinRarity":5,"weaponTypeDescription":"\u8FD1\u6230\u6B66\u5668","skinRarityDescription":"\u9650\u5B9A","score":8.043478260869565,"scoreCount":138,"rankNumberWithGSScoreDesc":0,"rankNumberWithGSScoreDescInWeapon":0,"ownersCount":224,"rankNumberWithOwnersCountDesc":0,"rankNumberWithOwnersCountDescInWeaponType":0,"rankNumberWithOwnersCountDescInWeapon":0,"isRecommended":false,"isRecommendedOfGlobal":false,"isRecommendedOfChianMainland":false,"isInSliderOfGlobal":false,"isInSliderOfChianMainland":false,"chromasCount":0,"levelCount":0,"ownedChromasCount":0,"ownedLevelCount":0,"publishTime":"2024/01/02 00:00:00","baseRefreshRate":0.006421878185319657},{"id":10319,"skinID":"A7547EE3-4143-A99C-D23C-11961C4336BD","isSetSkin":false,"skinSetName":"\u6975\u6A02\u4E4B\u9470","name":"\u6975\u6A02\u4E4B\u9470","name_SC":"\u5929\u5802\u4E4B\u94A5","weaponName":"\u795E\u5C04","weaponName_SC":"\u6B63\u4E49","picUrl":"https://img1b.gamersky.com/new/recommend/2026/05/06/origin_3845393_2058475.png","sliderImageUrl":"","price":0,"priceInDiscount":0,"discountExpireTime":"1970-01-01T08:00:00","discountStartTime":"1970-01-01T08:00:00","priceInChianMainland":0,"priceInDiscountInChianMainland":0,"discountExpireTimeInChianMainland":"1970-01-01T08:00:00","discountStartTimeInChianMainland":"1970-01-01T08:00:00","weaponType":1,"skinRarity":2,"weaponTypeDescription":"\u96A8\u8EAB\u6B66\u5668","skinRarityDescription":"\u5962\u83EF","score":8.23076923076923,"scoreCount":78,"rankNumberWithGSScoreDesc":0,"rankNumberWithGSScoreDescInWeapon":0,"ownersCount":297,"rankNumberWithOwnersCountDesc":0,"rankNumberWithOwnersCountDescInWeaponType":0,"rankNumberWithOwnersCountDescInWeapon":0,"isRecommended":false,"isRecommendedOfGlobal":false,"isRecommendedOfChianMainland":false,"isInSliderOfGlobal":false,"isInSliderOfChianMainland":false,"chromasCount":0,"levelCount":0,"ownedChromasCount":0,"ownedLevelCount":0,"publishTime":"2024/01/02 00:00:00","baseRefreshRate":0.006682441574373488},{"id":10317,"skinID":"6A752806-4097-BEFF-6EF2-9C8E27100D36","isSetSkin":false,"skinSetName":"\u6975\u6A02\u4E4B\u9470","name":"\u6975\u6A02\u4E4B\u9470","name_SC":"\u5929\u5802\u4E4B\u94A5","weaponName":"\u66B4\u5F92","weaponName_SC":"\u72C2\u5F92","picUrl":"https://img1b.gamersky.com/new/recommend/2026/05/06/origin_3845393_2058467.png","sliderImageUrl":"","price":0,"priceInDiscount":0,"discountExpireTime":"1970-01-01T08:00:00","discountStartTime":"1970-01-01T08:00:00","priceInChianMainland":0,"priceInDiscountInChianMainland":0,"discountExpireTimeInChianMainland":"1970-01-01T08:00:00","discountStartTimeInChianMainland":"1970-01-01T08:00:00","weaponType":3,"skinRarity":2,"weaponTypeDescription":"\u6B65\u69CD","skinRarityDescription":"\u5962\u83EF","score":7.714285714285714,"scoreCount":63,"rankNumberWithGSScoreDesc":0,"rankNumberWithGSScoreDescInWeapon":0,"ownersCount":4516,"rankNumberWithOwnersCountDesc":0,"rankNumberWithOwnersCountDescInWeaponType":0,"rankNumberWithOwnersCountDescInWeapon":0,"isRecommended":false,"isRecommendedOfGlobal":false,"isRecommendedOfChianMainland":false,"isInSliderOfGlobal":false,"isInSliderOfChianMainland":false,"chromasCount":0,"levelCount":0,"ownedChromasCount":0,"ownedLevelCount":0,"publishTime":"2024/01/02 00:00:00","baseRefreshRate":0.006759530000742305},{"id":10316,"skinID":"9ACCE26E-499D-BC02-98F2-22AF6F9CCA23","isSetSkin":false,"skinSetName":"\u6975\u6A02\u4E4B\u9470","name":"\u6975\u6A02\u4E4B\u9470","name_SC":"\u5929\u5802\u4E4B\u94A5","weaponName":"\u9003\u72AF","weaponName_SC":"\u83BD\u4FA0","picUrl":"https://img1b.gamersky.com/new/recommend/2026/05/06/origin_3845393_2058463.png","sliderImageUrl":"","price":0,"priceInDiscount":0,"discountExpireTime":"1970-01-01T08:00:00","discountStartTime":"1970-01-01T08:00:00","priceInChianMainland":0,"priceInDiscountInChianMainland":0,"discountExpireTimeInChianMainland":"1970-01-01T08:00:00","discountStartTimeInChianMainland":"1970-01-01T08:00:00","weaponType":4,"skinRarity":2,"weaponTypeDescription":"\u72D9\u64CA\u69CD","skinRarityDescription":"\u5962\u83EF","score":6.571428571428571,"scoreCount":42,"rankNumberWithGSScoreDesc":0,"rankNumberWithGSScoreDescInWeapon":0,"ownersCount":2672,"rankNumberWithOwnersCountDesc":0,"rankNumberWithOwnersCountDescInWeaponType":0,"rankNumberWithOwnersCountDescInWeapon":0,"isRecommended":false,"isRecommendedOfGlobal":false,"isRecommendedOfChianMainland":false,"isInSliderOfGlobal":false,"isInSliderOfChianMainland":false,"chromasCount":0,"levelCount":0,"ownedChromasCount":0,"ownedLevelCount":0,"publishTime":"2024/01/02 00:00:00","baseRefreshRate":0.007228272207187615},{"id":10315,"skinID":"8FE097F6-433F-546E-AAF2-5A99FED23576","isSetSkin":false,"skinSetName":"\u6975\u6A02\u4E4B\u9470","name":"\u6975\u6A02\u4E4B\u9470","name_SC":"\u5929\u5802\u4E4B\u94A5","weaponName":"\u6230\u795E","weaponName_SC":"\u6218\u795E","picUrl":"https://img1b.gamersky.com/new/recommend/2026/05/06/origin_3845393_2058459.png","sliderImageUrl":"","price":0,"priceInDiscount":0,"discountExpireTime":"1970-01-01T08:00:00","discountStartTime":"1970-01-01T08:00:00","priceInChianMainland":0,"priceInDiscountInChianMainland":0,"discountExpireTimeInChianMainland":"1970-01-01T08:00:00","discountStartTimeInChianMainland":"1970-01-01T08:00:00","weaponType":7,"skinRarity":2,"weaponTypeDescription":"\u6A5F\u95DC\u69CD","skinRarityDescription":"\u5962\u83EF","score":8,"scoreCount":33,"rankNumberWithGSScoreDesc":0,"rankNumberWithGSScoreDescInWeapon":0,"ownersCount":5508,"rankNumberWithOwnersCountDesc":0,"rankNumberWithOwnersCountDescInWeaponType":0,"rankNumberWithOwnersCountDescInWeapon":0,"isRecommended":false,"isRecommendedOfGlobal":false,"isRecommendedOfChianMainland":false,"isInSliderOfGlobal":false,"isInSliderOfChianMainland":false,"chromasCount":0,"levelCount":0,"ownedChromasCount":0,"ownedLevelCount":0,"publishTime":"2024/01/02 00:00:00","baseRefreshRate":0.007120842035916094},{"id":10314,"skinID":"04ECD04C-42B8-9475-DFA9-ABA597F877A1","isSetSkin":false,"skinSetName":"\u9670\u96AA\u6F5B\u4F0F","name":"\u9670\u96AA\u6F5B\u4F0F","name_SC":"\u6697\u591C\u68A6\u9B47","weaponName":"\u5E7B\u8C61","weaponName_SC":"\u5E7B\u5F71","picUrl":"https://img1b.gamersky.com/new/recommend/2026/05/06/origin_3845393_2058457.png","sliderImageUrl":"","price":0,"priceInDiscount":0,"discountExpireTime":"1970-01-01T08:00:00","discountStartTime":"1970-01-01T08:00:00","priceInChianMainland":0,"priceInDiscountInChianMainland":0,"discountExpireTimeInChianMainland":"1970-01-01T08:00:00","discountStartTimeInChianMainland":"1970-01-01T08:00:00","weaponType":3,"skinRarity":1,"weaponTypeDescription":"\u6B65\u69CD","skinRarityDescription":"\u7CBE\u9078","score":7.25,"scoreCount":8,"rankNumberWithGSScoreDesc":0,"rankNumberWithGSScoreDescInWeapon":0,"ownersCount":671,"rankNumberWithOwnersCountDesc":0,"rankNumberWithOwnersCountDescInWeaponType":0,"rankNumberWithOwnersCountDescInWeapon":0,"isRecommended":false,"isRecommendedOfGlobal":false,"isRecommendedOfChianMainland":false,"isInSliderOfGlobal":false,"isInSliderOfChianMainland":false,"chromasCount":0,"levelCount":0,"ownedChromasCount":0,"ownedLevelCount":0,"publishTime":"2024/01/02 00:00:00","baseRefreshRate":0.008988603296684381},{"id":10313,"skinID":"2940F37C-40CF-4094-FA0A-E9BFC62C0F5C","isSetSkin":false,"skinSetName":"\u9670\u96AA\u6F5B\u4F0F","name":"\u9670\u96AA\u6F5B\u4F0F","name_SC":"\u6697\u591C\u68A6\u9B47","weaponName":"\u5967\u4E01","weaponName_SC":"\u5965\u4E01","picUrl":"https://img1b.gamersky.com/new/recommend/2026/05/06/origin_3845393_2058458.png","sliderImageUrl":"","price":0,"priceInDiscount":0,"discountExpireTime":"1970-01-01T08:00:00","discountStartTime":"1970-01-01T08:00:00","priceInChianMainland":0,"priceInDiscountInChianMainland":0,"discountExpireTimeInChianMainland":"1970-01-01T08:00:00","discountStartTimeInChianMainland":"1970-01-01T08:00:00","weaponType":7,"skinRarity":1,"weaponTypeDescription":"\u6A5F\u95DC\u69CD","skinRarityDescription":"\u7CBE\u9078","score":6.571428571428571,"scoreCount":7,"rankNumberWithGSScoreDesc":0,"rankNumberWithGSScoreDescInWeapon":0,"ownersCount":3794,"rankNumberWithOwnersCountDesc":0,"rankNumberWithOwnersCountDescInWeaponType":0,"rankNumberWithOwnersCountDescInWeapon":0,"isRecommended":false,"isRecommendedOfGlobal":false,"isRecommendedOfChianMainland":false,"isInSliderOfGlobal":false,"isInSliderOfChianMainland":false,"chromasCount":0,"levelCount":0,"ownedChromasCount":0,"ownedLevelCount":0,"publishTime":"2024/01/02 00:00:00","baseRefreshRate":0.007889161817212198},{"id":10312,"skinID":"C6AD0BEF-4121-F0F2-1E24-9797BE0B4CEB","isSetSkin":false,"skinSetName":"\u9670\u96AA\u6F5B\u4F0F","name":"\u9670\u96AA\u6F5B\u4F0F","name_SC":"\u6697\u591C\u68A6\u9B47","weaponName":"\u8B66\u9577","weaponName_SC":"\u98DE\u5C06","picUrl":"https://img1b.gamersky.com/new/recommend/2026/05/06/origin_3845393_2058444.png","sliderImageUrl":"","price":0,"priceInDiscount":0,"discountExpireTime":"1970-01-01T08:00:00","discountStartTime":"1970-01-01T08:00:00","priceInChianMainland":0,"priceInDiscountInChianMainland":0,"discountExpireTimeInChianMainland":"1970-01-01T08:00:00","discountStartTimeInChianMainland":"1970-01-01T08:00:00","weaponType":4,"skinRarity":1,"weaponTypeDescription":"\u72D9\u64CA\u69CD","skinRarityDescription":"\u7CBE\u9078","score":4.666666666666667,"scoreCount":3,"rankNumberWithGSScoreDesc":0,"rankNumberWithGSScoreDescInWeapon":0,"ownersCount":5372,"rankNumberWithOwnersCountDesc":0,"rankNumberWithOwnersCountDescInWeaponType":0,"rankNumberWithOwnersCountDescInWeapon":0,"isRecommended":false,"isRecommendedOfGlobal":false,"isRecommendedOfChianMainland":false,"isInSliderOfGlobal":false,"isInSliderOfChianMainland":false,"chromasCount":0,"levelCount":0,"ownedChromasCount":0,"ownedLevelCount":0,"publishTime":"2024/01/02 00:00:00","baseRefreshRate":0.008623049691609595},{"id":10311,"skinID":"92B56CB5-4D2F-34D7-ABB2-F1A10CFF2026","isSetSkin":false,"skinSetName":"\u9670\u96AA\u6F5B\u4F0F","name":"\u9670\u96AA\u6F5B\u4F0F","name_SC":"\u6697\u591C\u68A6\u9B47","weaponName":"\u72C2\u5F12","weaponName_SC":"\u72C2\u6012","picUrl":"https://img1b.gamersky.com/new/recommend/2026/05/06/origin_3845393_2058440.png","sliderImageUrl":"","price":0,"priceInDiscount":0,"discountExpireTime":"1970-01-01T08:00:00","discountStartTime":"1970-01-01T08:00:00","priceInChianMainland":0,"priceInDiscountInChianMainland":0,"discountExpireTimeInChianMainland":"1970-01-01T08:00:00","discountStartTimeInChianMainland":"1970-01-01T08:00:00","weaponType":1,"skinRarity":1,"weaponTypeDescription":"\u96A8\u8EAB\u6B66\u5668","skinRarityDescription":"\u7CBE\u9078","score":6.25,"scoreCount":8,"rankNumberWithGSScoreDesc":0,"rankNumberWithGSScoreDescInWeapon":0,"ownersCount":5581,"rankNumberWithOwnersCountDesc":0,"rankNumberWithOwnersCountDescInWeaponType":0,"rankNumberWithOwnersCountDescInWeapon":0,"isRecommended":false,"isRecommendedOfGlobal":false,"isRecommendedOfChianMainland":false,"isInSliderOfGlobal":false,"isInSliderOfChianMainland":false,"chromasCount":0,"levelCount":0,"ownedChromasCount":0,"ownedLevelCount":0,"publishTime":"2024/01/02 00:00:00","baseRefreshRate":0.008414897291182957},{"id":10310,"skinID":"3A71AC66-4C4B-0D9A-89E8-A2A052030CBE","isSetSkin":false,"skinSetName":"\u60C5\u7DD2\u7206\u767C","name":"\u60C5\u7DD2\u7206\u767C","name_SC":"\u5931\u901F\u843D\u65E5","weaponName":"\u523A\u91DD","weaponName_SC":"\u8702\u523A","picUrl":"https://img1b.gamersky.com/new/recommend/2026/05/06/origin_3845393_2058439.png","sliderImageUrl":"","price":0,"priceInDiscount":0,"discountExpireTime":"1970-01-01T08:00:00","discountStartTime":"1970-01-01T08:00:00","priceInChianMainland":0,"priceInDiscountInChianMainland":0,"discountExpireTimeInChianMainland":"1970-01-01T08:00:00","discountStartTimeInChianMainland":"1970-01-01T08:00:00","weaponType":2,"skinRarity":1,"weaponTypeDescription":"\u885D\u92D2\u69CD","skinRarityDescription":"\u7CBE\u9078","score":2,"scoreCount":1,"rankNumberWithGSScoreDesc":0,"rankNumberWithGSScoreDescInWeapon":0,"ownersCount":5325,"rankNumberWithOwnersCountDesc":0,"rankNumberWithOwnersCountDescInWeaponType":0,"rankNumberWithOwnersCountDescInWeapon":0,"isRecommended":false,"isRecommendedOfGlobal":false,"isRecommendedOfChianMainland":false,"isInSliderOfGlobal":false,"isInSliderOfChianMainland":false,"chromasCount":0,"levelCount":0,"ownedChromasCount":0,"ownedLevelCount":0,"publishTime":"1970/01/01 08:00:00","baseRefreshRate":0.00802517805855031},{"id":10309,"skinID":"010C738B-4AC0-B4EA-D6D9-CCA5A62133C1","isSetSkin":false,"skinSetName":"\u60C5\u7DD2\u7206\u767C","name":"\u60C5\u7DD2\u7206\u767C","name_SC":"\u5931\u901F\u843D\u65E5","weaponName":"\u60E1\u9748","weaponName_SC":"\u9A87\u7075","picUrl":"https://img1b.gamersky.com/new/recommend/2026/05/06/origin_3845393_2058437.png","sliderImageUrl":"","price":0,"priceInDiscount":0,"discountExpireTime":"1970-01-01T08:00:00","discountStartTime":"1970-01-01T08:00:00","priceInChianMainland":0,"priceInDiscountInChianMainland":0,"discountExpireTimeInChianMainland":"1970-01-01T08:00:00","discountStartTimeInChianMainland":"1970-01-01T08:00:00","weaponType":2,"skinRarity":1,"weaponTypeDescription":"\u885D\u92D2\u69CD","skinRarityDescription":"\u7CBE\u9078","score":2,"scoreCount":1,"rankNumberWithGSScoreDesc":0,"rankNumberWithGSScoreDescInWeapon":0,"ownersCount":5553,"rankNumberWithOwnersCountDesc":0,"rankNumberWithOwnersCountDescInWeaponType":0,"rankNumberWithOwnersCountDescInWeapon":0,"isRecommended":false,"isRecommendedOfGlobal":false,"isRecommendedOfChianMainland":false,"isInSliderOfGlobal":false,"isInSliderOfChianMainland":false,"chromasCount":0,"levelCount":0,"ownedChromasCount":0,"ownedLevelCount":0,"publishTime":"1970/01/01 08:00:00","baseRefreshRate":0.008748801824519783},{"id":10308,"skinID":"A3B67CAB-47CF-A82A-A12F-4F86476DA1E5","isSetSkin":false,"skinSetName":"\u60C5\u7DD2\u7206\u767C","name":"\u60C5\u7DD2\u7206\u767C","name_SC":"\u5931\u901F\u843D\u65E5","weaponName":"\u91CD\u7832","weaponName_SC":"\u96C4\u9E7F","picUrl":"https://img1b.gamersky.com/new/recommend/2026/05/06/origin_3845393_2058434.png","sliderImageUrl":"","price":0,"priceInDiscount":0,"discountExpireTime":"1970-01-01T08:00:00","discountStartTime":"1970-01-01T08:00:00","priceInChianMainland":0,"priceInDiscountInChianMainland":0,"discountExpireTimeInChianMainland":"1970-01-01T08:00:00","discountStartTimeInChianMainland":"1970-01-01T08:00:00","weaponType":6,"skinRarity":1,"weaponTypeDescription":"\u9730\u5F48\u69CD","skinRarityDescription":"\u7CBE\u9078","score":6,"scoreCount":2,"rankNumberWithGSScoreDesc":0,"rankNumberWithGSScoreDescInWeapon":0,"ownersCount":1507,"rankNumberWithOwnersCountDesc":0,"rankNumberWithOwnersCountDescInWeaponType":0,"rankNumberWithOwnersCountDescInWeapon":0,"isRecommended":false,"isRecommendedOfGlobal":false,"isRecommendedOfChianMainland":false,"isInSliderOfGlobal":false,"isInSliderOfChianMainland":false,"chromasCount":0,"levelCount":0,"ownedChromasCount":0,"ownedLevelCount":0,"publishTime":"2024/01/02 00:00:00","baseRefreshRate":0.008415849669564445},{"id":10307,"skinID":"29F343B9-4387-B17F-DFDF-2BB1F66CD75B","isSetSkin":false,"skinSetName":"\u60C5\u7DD2\u7206\u767C","name":"\u60C5\u7DD2\u7206\u767C","name_SC":"\u5931\u901F\u843D\u65E5","weaponName":"\u76DC\u8CCA","weaponName_SC":"\u8FFD\u730E","picUrl":"https://img1b.gamersky.com/new/recommend/2026/05/06/origin_3845393_2058432.png","sliderImageUrl":"","price":0,"priceInDiscount":0,"discountExpireTime":"1970-01-01T08:00:00","discountStartTime":"1970-01-01T08:00:00","priceInChianMainland":0,"priceInDiscountInChianMainland":0,"discountExpireTimeInChianMainland":"1970-01-01T08:00:00","discountStartTimeInChianMainland":"1970-01-01T08:00:00","weaponType":1,"skinRarity":1,"weaponTypeDescription":"\u96A8\u8EAB\u6B66\u5668","skinRarityDescription":"\u7CBE\u9078","score":6,"scoreCount":4,"rankNumberWithGSScoreDesc":0,"rankNumberWithGSScoreDescInWeapon":0,"ownersCount":5024,"rankNumberWithOwnersCountDesc":0,"rankNumberWithOwnersCountDescInWeaponType":0,"rankNumberWithOwnersCountDescInWeapon":0,"isRecommended":false,"isRecommendedOfGlobal":false,"isRecommendedOfChianMainland":false,"isInSliderOfGlobal":false,"isInSliderOfChianMainland":false,"chromasCount":0,"levelCount":0,"ownedChromasCount":0,"ownedLevelCount":0,"publishTime":"2024/01/02 00:00:00","baseRefreshRate":0.007873415029083106},{"id":10248,"skinID":"664F9851-4B50-1B7B-97EB-C4B475A89ACD","isSetSkin":false,"skinSetName":"\u9ED1\u6CE22.0","name":"\u9ED1\u6CE2 \u9CF4\u795E","name_SC":"\u6CF7\u541F","weaponName":"\u8FD1\u6218","weaponName_SC":"\u8FD1\u6218","picUrl":"https://img1b.gamersky.com/new/recommend/2026/04/28/origin_6624212_2042162.png","sliderImageUrl":"","price":5350,"priceInDiscount":0,"discountExpireTime":"1970-01-01T08:00:00","discountStartTime":"1970-01-01T08:00:00","priceInChianMainland":3780,"priceInDiscountInChianMainland":0,"discountExpireTimeInChianMainland":"1970-01-01T08:00:00","discountStartTimeInChianMainland":"1970-01-01T08:00:00","weaponType":5,"skinRarity":5,"weaponTypeDescription":"\u8FD1\u6230\u6B66\u5668","skinRarityDescription":"\u9650\u5B9A","score":9.111283643892339,"scoreCount":11598,"rankNumberWithGSScoreDesc":97,"rankNumberWithGSScoreDescInWeapon":1,"ownersCount":5120,"rankNumberWithOwnersCountDesc":1119,"rankNumberWithOwnersCountDescInWeaponType":64,"rankNumberWithOwnersCountDescInWeapon":64,"isRecommended":false,"isRecommendedOfGlobal":false,"isRecommendedOfChianMainland":false,"isInSliderOfGlobal":false,"isInSliderOfChianMainland":false,"chromasCount":0,"levelCount":0,"ownedChromasCount":0,"ownedLevelCount":0,"publishTime":"2024/01/02 00:00:00","baseRefreshRate":0.00790093153198293},{"id":10247,"skinID":"0C989088-43EF-22AD-CC43-81A27BDE2377","isSetSkin":false,"skinSetName":"\u9ED1\u6CE22.0","name":"\u9ED1\u6CE22.0","name_SC":"\u5851\u6C34\u5B97//2.0","weaponName":"\u5E7B\u8C61","weaponName_SC":"\u5E7B\u5F71","picUrl":"https://img1b.gamersky.com/new/recommend/2026/04/28/origin_6624212_2042157.png","sliderImageUrl":"","price":2375,"priceInDiscount":0,"discountExpireTime":"1970-01-01T08:00:00","discountStartTime":"1970-01-01T08:00:00","priceInChianMainland":1690,"priceInDiscountInChianMainland":0,"discountExpireTimeInChianMainland":"1970-01-01T08:00:00","discountStartTimeInChianMainland":"1970-01-01T08:00:00","weaponType":3,"skinRarity":5,"weaponTypeDescription":"\u6B65\u69CD","skinRarityDescription":"\u9650\u5B9A","score":8.719390743995314,"scoreCount":5124,"rankNumberWithGSScoreDesc":362,"rankNumberWithGSScoreDescInWeapon":7,"ownersCount":3755,"rankNumberWithOwnersCountDesc":1371,"rankNumberWithOwnersCountDescInWeaponType":98,"rankNumberWithOwnersCountDescInWeapon":34,"isRecommended":false,"isRecommendedOfGlobal":false,"isRecommendedOfChianMainland":false,"isInSliderOfGlobal":false,"isInSliderOfChianMainland":false,"chromasCount":0,"levelCount":0,"ownedChromasCount":0,"ownedLevelCount":0,"publishTime":"2024/01/02 00:00:00","baseRefreshRate":0.008252326891409385},{"id":10246,"skinID":"34D29B9D-4672-EBE9-0795-508B66BA6551","isSetSkin":false,"skinSetName":"\u9ED1\u6CE22.0","name":"\u9ED1\u6CE22.0","name_SC":"\u5851\u6C34\u5B97//2.0","weaponName":"\u634D\u885B\u8005","weaponName_SC":"\u620D\u536B","picUrl":"https://img1b.gamersky.com/new/recommend/2026/04/28/origin_6624212_2042153.png","sliderImageUrl":"","price":2375,"priceInDiscount":0,"discountExpireTime":"1970-01-01T08:00:00","discountStartTime":"1970-01-01T08:00:00","priceInChianMainland":1690,"priceInDiscountInChianMainland":0,"discountExpireTimeInChianMainland":"1970-01-01T08:00:00","discountStartTimeInChianMainland":"1970-01-01T08:00:00","weaponType":3,"skinRarity":5,"weaponTypeDescription":"\u6B65\u69CD","skinRarityDescription":"\u9650\u5B9A","score":8.810509554140127,"scoreCount":3771,"rankNumberWithGSScoreDesc":268,"rankNumberWithGSScoreDescInWeapon":2,"ownersCount":3574,"rankNumberWithOwnersCountDesc":1423,"rankNumberWithOwnersCountDescInWeaponType":101,"rankNumberWithOwnersCountDescInWeapon":15,"isRecommended":false,"isRecommendedOfGlobal":false,"isRecommendedOfChianMainland":false,"isInSliderOfGlobal":false,"isInSliderOfChianMainland":false,"chromasCount":0,"levelCount":0,"ownedChromasCount":0,"ownedLevelCount":0,"publishTime":"2024/01/02 00:00:00","baseRefreshRate":0.006495255028128278},{"id":10245,"skinID":"70D67EB8-4D89-74D7-BEDB-398D3096A937","isSetSkin":false,"skinSetName":"\u9ED1\u6CE22.0","name":"\u9ED1\u6CE22.0","name_SC":"\u5851\u6C34\u5B97//2.0","weaponName":"\u9593\u8ADC","weaponName_SC":"\u51A5\u9A79","picUrl":"https://img1b.gamersky.com/new/recommend/2026/04/28/origin_6624212_2042149.png","sliderImageUrl":"","price":2375,"priceInDiscount":0,"discountExpireTime":"1970-01-01T08:00:00","discountStartTime":"1970-01-01T08:00:00","priceInChianMainland":1690,"priceInDiscountInChianMainland":0,"discountExpireTimeInChianMainland":"1970-01-01T08:00:00","discountStartTimeInChianMainland":"1970-01-01T08:00:00","weaponType":4,"skinRarity":5,"weaponTypeDescription":"\u72D9\u64CA\u69CD","skinRarityDescription":"\u9650\u5B9A","score":8.249641319942612,"scoreCount":2094,"rankNumberWithGSScoreDesc":968,"rankNumberWithGSScoreDescInWeapon":14,"ownersCount":3511,"rankNumberWithOwnersCountDesc":1444,"rankNumberWithOwnersCountDescInWeaponType":32,"rankNumberWithOwnersCountDescInWeapon":21,"isRecommended":false,"isRecommendedOfGlobal":false,"isRecommendedOfChianMainland":false,"isInSliderOfGlobal":false,"isInSliderOfChianMainland":false,"chromasCount":0,"levelCount":0,"ownedChromasCount":0,"ownedLevelCount":0,"publishTime":"2024/01/02 00:00:00","baseRefreshRate":0.008320193012859762},{"id":10244,"skinID":"CA55E031-4AD3-19AB-7C39-42840E4D6F4A","isSetSkin":false,"skinSetName":"\u9ED1\u6CE22.0","name":"\u9ED1\u6CE22.0","name_SC":"\u5851\u6C34\u5B97//2.0","weaponName":"\u9B3C\u9B45","weaponName_SC":"\u9B3C\u9B45","picUrl":"https://img1b.gamersky.com/new/recommend/2026/04/28/origin_6624212_2042145.png","sliderImageUrl":"","price":2375,"priceInDiscount":0,"discountExpireTime":"1970-01-01T08:00:00","discountStartTime":"1970-01-01T08:00:00","priceInChianMainland":1690,"priceInDiscountInChianMainland":0,"discountExpireTimeInChianMainland":"1970-01-01T08:00:00","discountStartTimeInChianMainland":"1970-01-01T08:00:00","weaponType":1,"skinRarity":5,"weaponTypeDescription":"\u96A8\u8EAB\u6B66\u5668","skinRarityDescription":"\u9650\u5B9A","score":8.880094506792675,"scoreCount":5082,"rankNumberWithGSScoreDesc":219,"rankNumberWithGSScoreDescInWeapon":1,"ownersCount":3918,"rankNumberWithOwnersCountDesc":1323,"rankNumberWithOwnersCountDescInWeaponType":66,"rankNumberWithOwnersCountDescInWeapon":17,"isRecommended":false,"isRecommendedOfGlobal":false,"isRecommendedOfChianMainland":false,"isInSliderOfGlobal":false,"isInSliderOfChianMainland":false,"chromasCount":0,"levelCount":0,"ownedChromasCount":0,"ownedLevelCount":0,"publishTime":"2024/01/02 00:00:00","baseRefreshRate":0.007595539228336671},{"id":10222,"skinID":"DC4F468B-4014-A989-BEB4-71A0F3160973","isSetSkin":false,"skinSetName":"\u94F6\u6CB3\u5B50\u5348\u7EBF","name":"\u5E7B\u5149\u9583\u8000","name_SC":"\u8680\u523B\u4E4B\u5203","weaponName":"\u8FD1\u6218","weaponName_SC":"\u8FD1\u6218","picUrl":"https://img1b.gamersky.com/new/recommend/2026/04/15/origin_6624212_2017538.png","sliderImageUrl":"","price":4350,"priceInDiscount":0,"discountExpireTime":"1970-01-01T08:00:00","discountStartTime":"1970-01-01T08:00:00","priceInChianMainland":3180,"priceInDiscountInChianMainland":0,"discountExpireTimeInChianMainland":"1970-01-01T08:00:00","discountStartTimeInChianMainland":"1970-01-01T08:00:00","weaponType":5,"skinRarity":5,"weaponTypeDescription":"\u8FD1\u6230\u6B66\u5668","skinRarityDescription":"\u9650\u5B9A","score":3.648,"scoreCount":753,"rankNumberWithGSScoreDesc":3178,"rankNumberWithGSScoreDescInWeapon":122,"ownersCount":217,"rankNumberWithOwnersCountDesc":2917,"rankNumberWithOwnersCountDescInWeaponType":122,"rankNumberWithOwnersCountDescInWeapon":122,"isRecommended":false,"isRecommendedOfGlobal":false,"isRecommendedOfChianMainland":false,"isInSliderOfGlobal":false,"isInSliderOfChianMainland":false,"chromasCount":0,"levelCount":0,"ownedChromasCount":0,"ownedLevelCount":0,"publishTime":"2024/01/02 00:00:00","baseRefreshRate":0.008066892672826951},{"id":10221,"skinID":"D7AA8579-45BC-8C0B-362B-02A704080D1B","isSetSkin":false,"skinSetName":"\u5E7B\u5149\u661F\u8ECC","name":"\u5E7B\u5149\u661F\u8ECC","name_SC":"\u94F6\u6CB3\u5B50\u5348\u7EBF","weaponName":"\u66B4\u5F92","weaponName_SC":"\u72C2\u5F92","picUrl":"https://img1b.gamersky.com/new/recommend/2026/04/15/origin_6624212_2017534.png","sliderImageUrl":"","price":2175,"priceInDiscount":0,"discountExpireTime":"1970-01-01T08:00:00","discountStartTime":"1970-01-01T08:00:00","priceInChianMainland":1590,"priceInDiscountInChianMainland":0,"discountExpireTimeInChianMainland":"1970-01-01T08:00:00","discountStartTimeInChianMainland":"1970-01-01T08:00:00","weaponType":3,"skinRarity":5,"weaponTypeDescription":"\u6B65\u69CD","skinRarityDescription":"\u9650\u5B9A","score":4.557142857142857,"scoreCount":1260,"rankNumberWithGSScoreDesc":3031,"rankNumberWithGSScoreDescInWeapon":59,"ownersCount":678,"rankNumberWithOwnersCountDesc":2547,"rankNumberWithOwnersCountDescInWeaponType":155,"rankNumberWithOwnersCountDescInWeapon":64,"isRecommended":false,"isRecommendedOfGlobal":false,"isRecommendedOfChianMainland":false,"isInSliderOfGlobal":false,"isInSliderOfChianMainland":false,"chromasCount":0,"levelCount":0,"ownedChromasCount":0,"ownedLevelCount":0,"publishTime":"2024/01/02 00:00:00","baseRefreshRate":0.007246996176078448}],"error":""}